{
  "step": 3,
  "timestamp": "2026-01-10T10:29:43.598506",
  "num_episodes": 160,
  "stats": {
    "objective/kl": 0.6001238822937012,
    "objective/kl_coef": 0.001,
    "objective/entropy": 40.91461944580078,
    "ppo/mean_non_score_reward": -0.00021822685084771365,
    "ppo/mean_scores": -0.4787134528160095,
    "ppo/std_scores": 0.957426905632019,
    "tokens/queries_len_mean": 508.0,
    "tokens/queries_len_std": 0.0,
    "tokens/responses_len_mean": 2.75,
    "tokens/responses_len_std": 0.9574270844459534,
    "ppo/loss/policy": 4.334883385581634e-08,
    "ppo/loss/value": 1.1912657022476196,
    "ppo/loss/total": 0.11912661790847778,
    "ppo/policy/entropy": 0.7619467377662659,
    "ppo/policy/approxkl": 0.0,
    "ppo/policy/policykl": 0.0,
    "ppo/policy/clipfrac": 0.0,
    "ppo/policy/advantages_mean": -4.334883385581634e-08,
    "ppo/returns/mean": -0.35821449756622314,
    "ppo/returns/var": 0.7770208716392517,
    "ppo/val/vpred": -1.5199841260910034,
    "ppo/val/error": 2.3825314044952393,
    "ppo/val/clipfrac": 0.0,
    "ppo/val/mean": -1.5199841260910034,
    "ppo/val/var": 0.3865257203578949,
    "ppo/val/var_explained": -2.0662386417388916,
    "ppo/learning_rate": 5e-06,
    "time/ppo/forward_pass": 0.6365227699279785,
    "time/ppo/compute_rewards": 0.0007083415985107422,
    "time/ppo/compute_advantages": 0.03563070297241211,
    "time/ppo/optimize_step": 0.7355527877807617,
    "time/ppo/calc_stats": 0.03270721435546875,
    "time/ppo/total": 1.4411659240722656,
    "mean_reward": 0.20000000298023224,
    "mean_score": 0.2,
    "success_rate": 0.2,
    "num_samples": 5,
    "num_batches": 1,
    "total_valid_turns": 5,
    "total_invalid_turns": 3645,
    "avg_valid_rate": 0.0023652389277389278
  },
  "episodes_summary": [
    {
      "task_id": 156342639,
      "game_name": "liars_dice",
      "seed": 198666607,
      "opponent": "random",
      "final_reward": 1.0,
      "total_turns": 2,
      "valid_turns": 0,
      "invalid_turns": 2,
      "valid_rate": 0.0
    },
    {
      "task_id": 217748121,
      "game_name": "leduc_poker",
      "seed": 88259957,
      "opponent": "random",
      "final_reward": 0.5384615384615384,
      "total_turns": 2,
      "valid_turns": 0,
      "invalid_turns": 2,
      "valid_rate": 0.0
    },
    {
      "task_id": 352855098,
      "game_name": "gin_rummy",
      "seed": 334668668,
      "opponent": "random",
      "final_reward": 0.5,
      "total_turns": 50,
      "valid_turns": 0,
      "invalid_turns": 50,
      "valid_rate": 0.0
    },
    {
      "task_id": 494243598,
      "game_name": "othello",
      "seed": 314439519,
      "opponent": "random",
      "final_reward": 0.0,
      "total_turns": 30,
      "valid_turns": 1,
      "invalid_turns": 29,
      "valid_rate": 0.03333333333333333
    },
    {
      "task_id": 617719461,
      "game_name": "hex",
      "seed": 1804881417,
      "opponent": "random",
      "final_reward": 1.0,
      "total_turns": 22,
      "valid_turns": 1,
      "invalid_turns": 21,
      "valid_rate": 0.045454545454545456
    },
    {
      "task_id": 40182997,
      "game_name": "goofspiel",
      "seed": 1789924707,
      "opponent": "random",
      "final_reward": 0.0,
      "total_turns": 0,
      "valid_turns": 0,
      "invalid_turns": 0,
      "valid_rate": 0.0
    },
    {
      "task_id": 199439071,
      "game_name": "liars_dice",
      "seed": 611102876,
      "opponent": "random",
      "final_reward": 0.0,
      "total_turns": 5,
      "valid_turns": 1,
      "invalid_turns": 4,
      "valid_rate": 0.2
    },
    {
      "task_id": 579332947,
      "game_name": "backgammon",
      "seed": 1813286854,
      "opponent": "random",
      "final_reward": 1.0,
      "total_turns": 38,
      "valid_turns": 0,
      "invalid_turns": 38,
      "valid_rate": 0.0
    },
    {
      "task_id": 740000655,
      "game_name": "clobber",
      "seed": 1522841287,
      "opponent": "random",
      "final_reward": 0.0,
      "total_turns": 13,
      "valid_turns": 1,
      "invalid_turns": 12,
      "valid_rate": 0.07692307692307693
    },
    {
      "task_id": 311348873,
      "game_name": "gin_rummy",
      "seed": 1065403167,
      "opponent": "random",
      "final_reward": 0.5,
      "total_turns": 65,
      "valid_turns": 0,
      "invalid_turns": 65,
      "valid_rate": 0.0
    },
    {
      "task_id": 559701542,
      "game_name": "backgammon",
      "seed": 1585942618,
      "opponent": "random",
      "final_reward": 1.0,
      "total_turns": 36,
      "valid_turns": 0,
      "invalid_turns": 36,
      "valid_rate": 0.0
    },
    {
      "task_id": 85502666,
      "game_name": "goofspiel",
      "seed": 248494427,
      "opponent": "random",
      "final_reward": 0.0,
      "total_turns": 0,
      "valid_turns": 0,
      "invalid_turns": 0,
      "valid_rate": 0.0
    },
    {
      "task_id": 250523814,
      "game_name": "leduc_poker",
      "seed": 1755036261,
      "opponent": "random",
      "final_reward": 0.46153846153846156,
      "total_turns": 1,
      "valid_turns": 0,
      "invalid_turns": 1,
      "valid_rate": 0.0
    },
    {
      "task_id": 301131134,
      "game_name": "gin_rummy",
      "seed": 1791969771,
      "opponent": "random",
      "final_reward": 0.5,
      "total_turns": 55,
      "valid_turns": 0,
      "invalid_turns": 55,
      "valid_rate": 0.0
    },
    {
      "task_id": 597734732,
      "game_name": "backgammon",
      "seed": 1377271479,
      "opponent": "random",
      "final_reward": 0.0,
      "total_turns": 38,
      "valid_turns": 0,
      "invalid_turns": 38,
      "valid_rate": 0.0
    },
    {
      "task_id": 59229932,
      "game_name": "goofspiel",
      "seed": 876131556,
      "opponent": "random",
      "final_reward": 1.0,
      "total_turns": 0,
      "valid_turns": 0,
      "invalid_turns": 0,
      "valid_rate": 0.0
    },
    {
      "task_id": 249874848,
      "game_name": "leduc_poker",
      "seed": 1259763940,
      "opponent": "random",
      "final_reward": 0.9230769230769231,
      "total_turns": 3,
      "valid_turns": 0,
      "invalid_turns": 3,
      "valid_rate": 0.0
    },
    {
      "task_id": 363201456,
      "game_name": "gin_rummy",
      "seed": 391084628,
      "opponent": "random",
      "final_reward": 0.5,
      "total_turns": 24,
      "valid_turns": 0,
      "invalid_turns": 24,
      "valid_rate": 0.0
    },
    {
      "task_id": 524891778,
      "game_name": "backgammon",
      "seed": 466499032,
      "opponent": "random",
      "final_reward": 1.0,
      "total_turns": 56,
      "valid_turns": 0,
      "invalid_turns": 56,
      "valid_rate": 0.0
    },
    {
      "task_id": 37174317,
      "game_name": "goofspiel",
      "seed": 481718119,
      "opponent": "random",
      "final_reward": 1.0,
      "total_turns": 0,
      "valid_turns": 0,
      "invalid_turns": 0,
      "valid_rate": 0.0
    },
    {
      "task_id": 274917864,
      "game_name": "leduc_poker",
      "seed": 660904546,
      "opponent": "random",
      "final_reward": 0.5384615384615384,
      "total_turns": 1,
      "valid_turns": 0,
      "invalid_turns": 1,
      "valid_rate": 0.0
    },
    {
      "task_id": 394301119,
      "game_name": "gin_rummy",
      "seed": 1916261408,
      "opponent": "random",
      "final_reward": 0.5,
      "total_turns": 59,
      "valid_turns": 0,
      "invalid_turns": 59,
      "valid_rate": 0.0
    },
    {
      "task_id": 553522930,
      "game_name": "backgammon",
      "seed": 796203998,
      "opponent": "random",
      "final_reward": 0.0,
      "total_turns": 84,
      "valid_turns": 0,
      "invalid_turns": 84,
      "valid_rate": 0.0
    },
    {
      "task_id": 56600194,
      "game_name": "goofspiel",
      "seed": 1854208234,
      "opponent": "random",
      "final_reward": 0.0,
      "total_turns": 0,
      "valid_turns": 0,
      "invalid_turns": 0,
      "valid_rate": 0.0
    },
    {
      "task_id": 223452830,
      "game_name": "leduc_poker",
      "seed": 1064970056,
      "opponent": "random",
      "final_reward": 0.6923076923076923,
      "total_turns": 3,
      "valid_turns": 0,
      "invalid_turns": 3,
      "valid_rate": 0.0
    },
    {
      "task_id": 360860630,
      "game_name": "gin_rummy",
      "seed": 1461954905,
      "opponent": "random",
      "final_reward": 0.5,
      "total_turns": 70,
      "valid_turns": 0,
      "invalid_turns": 70,
      "valid_rate": 0.0
    },
    {
      "task_id": 570242666,
      "game_name": "backgammon",
      "seed": 612322711,
      "opponent": "random",
      "final_reward": 0.0,
      "total_turns": 55,
      "valid_turns": 0,
      "invalid_turns": 55,
      "valid_rate": 0.0
    },
    {
      "task_id": 47696611,
      "game_name": "goofspiel",
      "seed": 1986144716,
      "opponent": "random",
      "final_reward": 0.0,
      "total_turns": 0,
      "valid_turns": 0,
      "invalid_turns": 0,
      "valid_rate": 0.0
    },
    {
      "task_id": 284760766,
      "game_name": "leduc_poker",
      "seed": 371512088,
      "opponent": "random",
      "final_reward": 0.38461538461538464,
      "total_turns": 2,
      "valid_turns": 0,
      "invalid_turns": 2,
      "valid_rate": 0.0
    },
    {
      "task_id": 364865815,
      "game_name": "gin_rummy",
      "seed": 874626735,
      "opponent": "random",
      "final_reward": 0.5,
      "total_turns": 77,
      "valid_turns": 0,
      "invalid_turns": 77,
      "valid_rate": 0.0
    },
    {
      "task_id": 539557766,
      "game_name": "backgammon",
      "seed": 7916306,
      "opponent": "random",
      "final_reward": 1.0,
      "total_turns": 54,
      "valid_turns": 0,
      "invalid_turns": 54,
      "valid_rate": 0.0
    },
    {
      "task_id": 93817079,
      "game_name": "goofspiel",
      "seed": 1928819889,
      "opponent": "random",
      "final_reward": 0.0,
      "total_turns": 0,
      "valid_turns": 0,
      "invalid_turns": 0,
      "valid_rate": 0.0
    },
    {
      "task_id": 283045275,
      "game_name": "leduc_poker",
      "seed": 1984321482,
      "opponent": "random",
      "final_reward": 0.5,
      "total_turns": 2,
      "valid_turns": 0,
      "invalid_turns": 2,
      "valid_rate": 0.0
    },
    {
      "task_id": 301043764,
      "game_name": "gin_rummy",
      "seed": 939456181,
      "opponent": "random",
      "final_reward": 0.5,
      "total_turns": 62,
      "valid_turns": 0,
      "invalid_turns": 62,
      "valid_rate": 0.0
    },
    {
      "task_id": 540072061,
      "game_name": "backgammon",
      "seed": 491590016,
      "opponent": "random",
      "final_reward": 1.0,
      "total_turns": 29,
      "valid_turns": 0,
      "invalid_turns": 29,
      "valid_rate": 0.0
    },
    {
      "task_id": 84412264,
      "game_name": "goofspiel",
      "seed": 1293467907,
      "opponent": "random",
      "final_reward": 1.0,
      "total_turns": 0,
      "valid_turns": 0,
      "invalid_turns": 0,
      "valid_rate": 0.0
    },
    {
      "task_id": 273176594,
      "game_name": "leduc_poker",
      "seed": 670964555,
      "opponent": "random",
      "final_reward": 0.6923076923076923,
      "total_turns": 2,
      "valid_turns": 0,
      "invalid_turns": 2,
      "valid_rate": 0.0
    },
    {
      "task_id": 356936377,
      "game_name": "gin_rummy",
      "seed": 2024797582,
      "opponent": "random",
      "final_reward": 0.5,
      "total_turns": 12,
      "valid_turns": 0,
      "invalid_turns": 12,
      "valid_rate": 0.0
    },
    {
      "task_id": 512422259,
      "game_name": "backgammon",
      "seed": 2137517594,
      "opponent": "random",
      "final_reward": 1.0,
      "total_turns": 59,
      "valid_turns": 0,
      "invalid_turns": 59,
      "valid_rate": 0.0
    },
    {
      "task_id": 31187196,
      "game_name": "goofspiel",
      "seed": 1740772181,
      "opponent": "random",
      "final_reward": 0.0,
      "total_turns": 0,
      "valid_turns": 0,
      "invalid_turns": 0,
      "valid_rate": 0.0
    },
    {
      "task_id": 237592826,
      "game_name": "leduc_poker",
      "seed": 92854557,
      "opponent": "random",
      "final_reward": 0.7692307692307693,
      "total_turns": 2,
      "valid_turns": 0,
      "invalid_turns": 2,
      "valid_rate": 0.0
    },
    {
      "task_id": 316217744,
      "game_name": "gin_rummy",
      "seed": 1159977915,
      "opponent": "random",
      "final_reward": 0.5,
      "total_turns": 35,
      "valid_turns": 0,
      "invalid_turns": 35,
      "valid_rate": 0.0
    },
    {
      "task_id": 589723030,
      "game_name": "backgammon",
      "seed": 174148579,
      "opponent": "random",
      "final_reward": 0.0,
      "total_turns": 82,
      "valid_turns": 0,
      "invalid_turns": 82,
      "valid_rate": 0.0
    },
    {
      "task_id": 33985,
      "game_name": "goofspiel",
      "seed": 1101984759,
      "opponent": "random",
      "final_reward": 0.0,
      "total_turns": 0,
      "valid_turns": 0,
      "invalid_turns": 0,
      "valid_rate": 0.0
    },
    {
      "task_id": 253476182,
      "game_name": "leduc_poker",
      "seed": 1701816294,
      "opponent": "random",
      "final_reward": 0.6923076923076923,
      "total_turns": 2,
      "valid_turns": 0,
      "invalid_turns": 2,
      "valid_rate": 0.0
    },
    {
      "task_id": 359671128,
      "game_name": "gin_rummy",
      "seed": 438222914,
      "opponent": "random",
      "final_reward": 0.5,
      "total_turns": 78,
      "valid_turns": 0,
      "invalid_turns": 78,
      "valid_rate": 0.0
    },
    {
      "task_id": 533904483,
      "game_name": "backgammon",
      "seed": 1519654072,
      "opponent": "random",
      "final_reward": 1.0,
      "total_turns": 33,
      "valid_turns": 0,
      "invalid_turns": 33,
      "valid_rate": 0.0
    },
    {
      "task_id": 38036834,
      "game_name": "goofspiel",
      "seed": 841946265,
      "opponent": "random",
      "final_reward": 1.0,
      "total_turns": 0,
      "valid_turns": 0,
      "invalid_turns": 0,
      "valid_rate": 0.0
    },
    {
      "task_id": 279914566,
      "game_name": "leduc_poker",
      "seed": 366185641,
      "opponent": "random",
      "final_reward": 0.46153846153846156,
      "total_turns": 2,
      "valid_turns": 0,
      "invalid_turns": 2,
      "valid_rate": 0.0
    },
    {
      "task_id": 304758148,
      "game_name": "gin_rummy",
      "seed": 302604778,
      "opponent": "random",
      "final_reward": 0.5,
      "total_turns": 83,
      "valid_turns": 0,
      "invalid_turns": 83,
      "valid_rate": 0.0
    },
    {
      "task_id": 535230380,
      "game_name": "backgammon",
      "seed": 1312558893,
      "opponent": "random",
      "final_reward": 0.0,
      "total_turns": 54,
      "valid_turns": 0,
      "invalid_turns": 54,
      "valid_rate": 0.0
    },
    {
      "task_id": 71623767,
      "game_name": "goofspiel",
      "seed": 1459818206,
      "opponent": "random",
      "final_reward": 1.0,
      "total_turns": 0,
      "valid_turns": 0,
      "invalid_turns": 0,
      "valid_rate": 0.0
    },
    {
      "task_id": 215862498,
      "game_name": "leduc_poker",
      "seed": 1069648896,
      "opponent": "random",
      "final_reward": 0.5,
      "total_turns": 2,
      "valid_turns": 0,
      "invalid_turns": 2,
      "valid_rate": 0.0
    },
    {
      "task_id": 321951948,
      "game_name": "gin_rummy",
      "seed": 292457060,
      "opponent": "random",
      "final_reward": 0.5,
      "total_turns": 60,
      "valid_turns": 0,
      "invalid_turns": 60,
      "valid_rate": 0.0
    },
    {
      "task_id": 555677593,
      "game_name": "backgammon",
      "seed": 1244217447,
      "opponent": "random",
      "final_reward": 1.0,
      "total_turns": 28,
      "valid_turns": 0,
      "invalid_turns": 28,
      "valid_rate": 0.0
    },
    {
      "task_id": 37949779,
      "game_name": "goofspiel",
      "seed": 577331751,
      "opponent": "random",
      "final_reward": 1.0,
      "total_turns": 0,
      "valid_turns": 0,
      "invalid_turns": 0,
      "valid_rate": 0.0
    },
    {
      "task_id": 277038533,
      "game_name": "leduc_poker",
      "seed": 903138613,
      "opponent": "random",
      "final_reward": 0.6153846153846154,
      "total_turns": 1,
      "valid_turns": 0,
      "invalid_turns": 1,
      "valid_rate": 0.0
    },
    {
      "task_id": 371320053,
      "game_name": "gin_rummy",
      "seed": 452287526,
      "opponent": "random",
      "final_reward": 0.5,
      "total_turns": 70,
      "valid_turns": 0,
      "invalid_turns": 70,
      "valid_rate": 0.0
    },
    {
      "task_id": 555137246,
      "game_name": "backgammon",
      "seed": 1732645099,
      "opponent": "random",
      "final_reward": 1.0,
      "total_turns": 44,
      "valid_turns": 0,
      "invalid_turns": 44,
      "valid_rate": 0.0
    },
    {
      "task_id": 99512655,
      "game_name": "goofspiel",
      "seed": 1196640594,
      "opponent": "random",
      "final_reward": 1.0,
      "total_turns": 0,
      "valid_turns": 0,
      "invalid_turns": 0,
      "valid_rate": 0.0
    },
    {
      "task_id": 239225690,
      "game_name": "leduc_poker",
      "seed": 1899941553,
      "opponent": "random",
      "final_reward": 0.5384615384615384,
      "total_turns": 2,
      "valid_turns": 0,
      "invalid_turns": 2,
      "valid_rate": 0.0
    },
    {
      "task_id": 349902731,
      "game_name": "gin_rummy",
      "seed": 591901263,
      "opponent": "random",
      "final_reward": 0.5,
      "total_turns": 60,
      "valid_turns": 0,
      "invalid_turns": 60,
      "valid_rate": 0.0
    },
    {
      "task_id": 521081574,
      "game_name": "backgammon",
      "seed": 529561813,
      "opponent": "random",
      "final_reward": 1.0,
      "total_turns": 72,
      "valid_turns": 0,
      "invalid_turns": 72,
      "valid_rate": 0.0
    },
    {
      "task_id": 93554042,
      "game_name": "goofspiel",
      "seed": 517620233,
      "opponent": "random",
      "final_reward": 0.0,
      "total_turns": 0,
      "valid_turns": 0,
      "invalid_turns": 0,
      "valid_rate": 0.0
    },
    {
      "task_id": 251194366,
      "game_name": "leduc_poker",
      "seed": 1723211911,
      "opponent": "random",
      "final_reward": 0.5,
      "total_turns": 2,
      "valid_turns": 0,
      "invalid_turns": 2,
      "valid_rate": 0.0
    },
    {
      "task_id": 379331062,
      "game_name": "gin_rummy",
      "seed": 2009799207,
      "opponent": "random",
      "final_reward": 0.5,
      "total_turns": 66,
      "valid_turns": 0,
      "invalid_turns": 66,
      "valid_rate": 0.0
    },
    {
      "task_id": 518727815,
      "game_name": "backgammon",
      "seed": 1284028888,
      "opponent": "random",
      "final_reward": 1.0,
      "total_turns": 86,
      "valid_turns": 0,
      "invalid_turns": 86,
      "valid_rate": 0.0
    },
    {
      "task_id": 47520841,
      "game_name": "goofspiel",
      "seed": 2030083169,
      "opponent": "random",
      "final_reward": 0.0,
      "total_turns": 0,
      "valid_turns": 0,
      "invalid_turns": 0,
      "valid_rate": 0.0
    },
    {
      "task_id": 299635922,
      "game_name": "leduc_poker",
      "seed": 1782872720,
      "opponent": "random",
      "final_reward": 0.5384615384615384,
      "total_turns": 1,
      "valid_turns": 0,
      "invalid_turns": 1,
      "valid_rate": 0.0
    },
    {
      "task_id": 329260801,
      "game_name": "gin_rummy",
      "seed": 2047476410,
      "opponent": "random",
      "final_reward": 0.3699186991869919,
      "total_turns": 9,
      "valid_turns": 0,
      "invalid_turns": 9,
      "valid_rate": 0.0
    },
    {
      "task_id": 565613431,
      "game_name": "backgammon",
      "seed": 1366831154,
      "opponent": "random",
      "final_reward": 0.0,
      "total_turns": 43,
      "valid_turns": 0,
      "invalid_turns": 43,
      "valid_rate": 0.0
    },
    {
      "task_id": 66131725,
      "game_name": "goofspiel",
      "seed": 258651995,
      "opponent": "random",
      "final_reward": 0.0,
      "total_turns": 0,
      "valid_turns": 0,
      "invalid_turns": 0,
      "valid_rate": 0.0
    },
    {
      "task_id": 259590222,
      "game_name": "leduc_poker",
      "seed": 1289285412,
      "opponent": "random",
      "final_reward": 0.5384615384615384,
      "total_turns": 1,
      "valid_turns": 0,
      "invalid_turns": 1,
      "valid_rate": 0.0
    },
    {
      "task_id": 319167825,
      "game_name": "gin_rummy",
      "seed": 2128255673,
      "opponent": "random",
      "final_reward": 0.6910569105691057,
      "total_turns": 35,
      "valid_turns": 0,
      "invalid_turns": 35,
      "valid_rate": 0.0
    },
    {
      "task_id": 507033797,
      "game_name": "backgammon",
      "seed": 926484330,
      "opponent": "random",
      "final_reward": 0.0,
      "total_turns": 44,
      "valid_turns": 1,
      "invalid_turns": 43,
      "valid_rate": 0.022727272727272728
    },
    {
      "task_id": 203428833,
      "game_name": "leduc_poker",
      "seed": 1526437221,
      "opponent": "random",
      "final_reward": 0.46153846153846156,
      "total_turns": 1,
      "valid_turns": 0,
      "invalid_turns": 1,
      "valid_rate": 0.0
    },
    {
      "task_id": 363287533,
      "game_name": "gin_rummy",
      "seed": 1679186368,
      "opponent": "random",
      "final_reward": 0.5,
      "total_turns": 69,
      "valid_turns": 0,
      "invalid_turns": 69,
      "valid_rate": 0.0
    },
    {
      "task_id": 1356953,
      "game_name": "goofspiel",
      "seed": 285429891,
      "opponent": "random",
      "final_reward": 1.0,
      "total_turns": 0,
      "valid_turns": 0,
      "invalid_turns": 0,
      "valid_rate": 0.0
    },
    {
      "task_id": 292193569,
      "game_name": "leduc_poker",
      "seed": 349493974,
      "opponent": "random",
      "final_reward": 0.5384615384615384,
      "total_turns": 1,
      "valid_turns": 0,
      "invalid_turns": 1,
      "valid_rate": 0.0
    },
    {
      "task_id": 392113159,
      "game_name": "gin_rummy",
      "seed": 1697007969,
      "opponent": "random",
      "final_reward": 0.5,
      "total_turns": 72,
      "valid_turns": 0,
      "invalid_turns": 72,
      "valid_rate": 0.0
    },
    {
      "task_id": 862141,
      "game_name": "goofspiel",
      "seed": 1551678562,
      "opponent": "random",
      "final_reward": 0.0,
      "total_turns": 0,
      "valid_turns": 0,
      "invalid_turns": 0,
      "valid_rate": 0.0
    },
    {
      "task_id": 205526799,
      "game_name": "leduc_poker",
      "seed": 498869501,
      "opponent": "random",
      "final_reward": 0.6153846153846154,
      "total_turns": 2,
      "valid_turns": 0,
      "invalid_turns": 2,
      "valid_rate": 0.0
    },
    {
      "task_id": 383332674,
      "game_name": "gin_rummy",
      "seed": 16064756,
      "opponent": "random",
      "final_reward": 0.5,
      "total_turns": 74,
      "valid_turns": 0,
      "invalid_turns": 74,
      "valid_rate": 0.0
    },
    {
      "task_id": 36282774,
      "game_name": "goofspiel",
      "seed": 1256391411,
      "opponent": "random",
      "final_reward": 0.0,
      "total_turns": 0,
      "valid_turns": 0,
      "invalid_turns": 0,
      "valid_rate": 0.0
    },
    {
      "task_id": 297589703,
      "game_name": "leduc_poker",
      "seed": 973613345,
      "opponent": "random",
      "final_reward": 0.38461538461538464,
      "total_turns": 2,
      "valid_turns": 0,
      "invalid_turns": 2,
      "valid_rate": 0.0
    },
    {
      "task_id": 318881721,
      "game_name": "gin_rummy",
      "seed": 1236624635,
      "opponent": "random",
      "final_reward": 0.5,
      "total_turns": 68,
      "valid_turns": 0,
      "invalid_turns": 68,
      "valid_rate": 0.0
    },
    {
      "task_id": 25663012,
      "game_name": "goofspiel",
      "seed": 452948398,
      "opponent": "random",
      "final_reward": 1.0,
      "total_turns": 0,
      "valid_turns": 0,
      "invalid_turns": 0,
      "valid_rate": 0.0
    },
    {
      "task_id": 258253032,
      "game_name": "leduc_poker",
      "seed": 1979528503,
      "opponent": "random",
      "final_reward": 0.5384615384615384,
      "total_turns": 2,
      "valid_turns": 0,
      "invalid_turns": 2,
      "valid_rate": 0.0
    },
    {
      "task_id": 396146298,
      "game_name": "gin_rummy",
      "seed": 1418180035,
      "opponent": "random",
      "final_reward": 0.5,
      "total_turns": 71,
      "valid_turns": 0,
      "invalid_turns": 71,
      "valid_rate": 0.0
    },
    {
      "task_id": 51557076,
      "game_name": "goofspiel",
      "seed": 722651436,
      "opponent": "random",
      "final_reward": 1.0,
      "total_turns": 0,
      "valid_turns": 0,
      "invalid_turns": 0,
      "valid_rate": 0.0
    },
    {
      "task_id": 244385201,
      "game_name": "leduc_poker",
      "seed": 1811230205,
      "opponent": "random",
      "final_reward": 0.7692307692307693,
      "total_turns": 2,
      "valid_turns": 0,
      "invalid_turns": 2,
      "valid_rate": 0.0
    },
    {
      "task_id": 386973752,
      "game_name": "gin_rummy",
      "seed": 1869471609,
      "opponent": "random",
      "final_reward": 0.5,
      "total_turns": 69,
      "valid_turns": 0,
      "invalid_turns": 69,
      "valid_rate": 0.0
    },
    {
      "task_id": 19866812,
      "game_name": "goofspiel",
      "seed": 1921104041,
      "opponent": "random",
      "final_reward": 0.0,
      "total_turns": 0,
      "valid_turns": 0,
      "invalid_turns": 0,
      "valid_rate": 0.0
    },
    {
      "task_id": 295137251,
      "game_name": "leduc_poker",
      "seed": 633510762,
      "opponent": "random",
      "final_reward": 0.5384615384615384,
      "total_turns": 2,
      "valid_turns": 0,
      "invalid_turns": 2,
      "valid_rate": 0.0
    },
    {
      "task_id": 370351815,
      "game_name": "gin_rummy",
      "seed": 1357517604,
      "opponent": "random",
      "final_reward": 0.5,
      "total_turns": 64,
      "valid_turns": 0,
      "invalid_turns": 64,
      "valid_rate": 0.0
    },
    {
      "task_id": 17344022,
      "game_name": "goofspiel",
      "seed": 897072998,
      "opponent": "random",
      "final_reward": 0.0,
      "total_turns": 0,
      "valid_turns": 0,
      "invalid_turns": 0,
      "valid_rate": 0.0
    },
    {
      "task_id": 225075151,
      "game_name": "leduc_poker",
      "seed": 1907499492,
      "opponent": "random",
      "final_reward": 0.6153846153846154,
      "total_turns": 2,
      "valid_turns": 0,
      "invalid_turns": 2,
      "valid_rate": 0.0
    },
    {
      "task_id": 346864429,
      "game_name": "gin_rummy",
      "seed": 1670205978,
      "opponent": "random",
      "final_reward": 0.5,
      "total_turns": 40,
      "valid_turns": 0,
      "invalid_turns": 40,
      "valid_rate": 0.0
    },
    {
      "task_id": 57349920,
      "game_name": "goofspiel",
      "seed": 2112945771,
      "opponent": "random",
      "final_reward": 1.0,
      "total_turns": 0,
      "valid_turns": 0,
      "invalid_turns": 0,
      "valid_rate": 0.0
    },
    {
      "task_id": 252282692,
      "game_name": "leduc_poker",
      "seed": 945577948,
      "opponent": "random",
      "final_reward": 0.6923076923076923,
      "total_turns": 2,
      "valid_turns": 0,
      "invalid_turns": 2,
      "valid_rate": 0.0
    },
    {
      "task_id": 326332802,
      "game_name": "gin_rummy",
      "seed": 1886659028,
      "opponent": "random",
      "final_reward": 0.5,
      "total_turns": 6,
      "valid_turns": 0,
      "invalid_turns": 6,
      "valid_rate": 0.0
    },
    {
      "task_id": 27416482,
      "game_name": "goofspiel",
      "seed": 213860429,
      "opponent": "random",
      "final_reward": 0.0,
      "total_turns": 0,
      "valid_turns": 0,
      "invalid_turns": 0,
      "valid_rate": 0.0
    },
    {
      "task_id": 252123132,
      "game_name": "leduc_poker",
      "seed": 142933270,
      "opponent": "random",
      "final_reward": 0.6153846153846154,
      "total_turns": 2,
      "valid_turns": 0,
      "invalid_turns": 2,
      "valid_rate": 0.0
    },
    {
      "task_id": 331410875,
      "game_name": "gin_rummy",
      "seed": 363599299,
      "opponent": "random",
      "final_reward": 0.5,
      "total_turns": 69,
      "valid_turns": 0,
      "invalid_turns": 69,
      "valid_rate": 0.0
    },
    {
      "task_id": 25065948,
      "game_name": "goofspiel",
      "seed": 1561693764,
      "opponent": "random",
      "final_reward": 1.0,
      "total_turns": 0,
      "valid_turns": 0,
      "invalid_turns": 0,
      "valid_rate": 0.0
    },
    {
      "task_id": 207649132,
      "game_name": "leduc_poker",
      "seed": 744635075,
      "opponent": "random",
      "final_reward": 0.46153846153846156,
      "total_turns": 1,
      "valid_turns": 0,
      "invalid_turns": 1,
      "valid_rate": 0.0
    },
    {
      "task_id": 331281343,
      "game_name": "gin_rummy",
      "seed": 1277869482,
      "opponent": "random",
      "final_reward": 0.5,
      "total_turns": 36,
      "valid_turns": 0,
      "invalid_turns": 36,
      "valid_rate": 0.0
    },
    {
      "task_id": 82209264,
      "game_name": "goofspiel",
      "seed": 372071538,
      "opponent": "random",
      "final_reward": 1.0,
      "total_turns": 0,
      "valid_turns": 0,
      "invalid_turns": 0,
      "valid_rate": 0.0
    },
    {
      "task_id": 294613258,
      "game_name": "leduc_poker",
      "seed": 1221591742,
      "opponent": "random",
      "final_reward": 0.5,
      "total_turns": 2,
      "valid_turns": 0,
      "invalid_turns": 2,
      "valid_rate": 0.0
    },
    {
      "task_id": 347388398,
      "game_name": "gin_rummy",
      "seed": 1767088405,
      "opponent": "random",
      "final_reward": 0.5,
      "total_turns": 63,
      "valid_turns": 0,
      "invalid_turns": 63,
      "valid_rate": 0.0
    },
    {
      "task_id": 61511223,
      "game_name": "goofspiel",
      "seed": 231670619,
      "opponent": "random",
      "final_reward": 0.0,
      "total_turns": 0,
      "valid_turns": 0,
      "invalid_turns": 0,
      "valid_rate": 0.0
    },
    {
      "task_id": 284809421,
      "game_name": "leduc_poker",
      "seed": 1849432265,
      "opponent": "random",
      "final_reward": 0.5,
      "total_turns": 2,
      "valid_turns": 0,
      "invalid_turns": 2,
      "valid_rate": 0.0
    },
    {
      "task_id": 377975149,
      "game_name": "gin_rummy",
      "seed": 1952502285,
      "opponent": "random",
      "final_reward": 0.5,
      "total_turns": 44,
      "valid_turns": 0,
      "invalid_turns": 44,
      "valid_rate": 0.0
    },
    {
      "task_id": 65793807,
      "game_name": "goofspiel",
      "seed": 1094152418,
      "opponent": "random",
      "final_reward": 0.0,
      "total_turns": 0,
      "valid_turns": 0,
      "invalid_turns": 0,
      "valid_rate": 0.0
    },
    {
      "task_id": 294504959,
      "game_name": "leduc_poker",
      "seed": 2042911800,
      "opponent": "random",
      "final_reward": 0.46153846153846156,
      "total_turns": 2,
      "valid_turns": 0,
      "invalid_turns": 2,
      "valid_rate": 0.0
    },
    {
      "task_id": 328913128,
      "game_name": "gin_rummy",
      "seed": 1448238304,
      "opponent": "random",
      "final_reward": 0.5,
      "total_turns": 67,
      "valid_turns": 0,
      "invalid_turns": 67,
      "valid_rate": 0.0
    },
    {
      "task_id": 35684741,
      "game_name": "goofspiel",
      "seed": 181398436,
      "opponent": "random",
      "final_reward": 1.0,
      "total_turns": 0,
      "valid_turns": 0,
      "invalid_turns": 0,
      "valid_rate": 0.0
    },
    {
      "task_id": 205879710,
      "game_name": "leduc_poker",
      "seed": 225714774,
      "opponent": "random",
      "final_reward": 0.9230769230769231,
      "total_turns": 3,
      "valid_turns": 0,
      "invalid_turns": 3,
      "valid_rate": 0.0
    },
    {
      "task_id": 321858369,
      "game_name": "gin_rummy",
      "seed": 1502389172,
      "opponent": "random",
      "final_reward": 0.5,
      "total_turns": 49,
      "valid_turns": 0,
      "invalid_turns": 49,
      "valid_rate": 0.0
    },
    {
      "task_id": 520033,
      "game_name": "goofspiel",
      "seed": 1244723149,
      "opponent": "random",
      "final_reward": 0.0,
      "total_turns": 0,
      "valid_turns": 0,
      "invalid_turns": 0,
      "valid_rate": 0.0
    },
    {
      "task_id": 287862626,
      "game_name": "leduc_poker",
      "seed": 30623376,
      "opponent": "random",
      "final_reward": 0.6153846153846154,
      "total_turns": 2,
      "valid_turns": 0,
      "invalid_turns": 2,
      "valid_rate": 0.0
    },
    {
      "task_id": 318845107,
      "game_name": "gin_rummy",
      "seed": 273547110,
      "opponent": "random",
      "final_reward": 0.5,
      "total_turns": 31,
      "valid_turns": 0,
      "invalid_turns": 31,
      "valid_rate": 0.0
    },
    {
      "task_id": 57410904,
      "game_name": "goofspiel",
      "seed": 954197867,
      "opponent": "random",
      "final_reward": 0.0,
      "total_turns": 0,
      "valid_turns": 0,
      "invalid_turns": 0,
      "valid_rate": 0.0
    },
    {
      "task_id": 281689998,
      "game_name": "leduc_poker",
      "seed": 1703016756,
      "opponent": "random",
      "final_reward": 0.9230769230769231,
      "total_turns": 3,
      "valid_turns": 0,
      "invalid_turns": 3,
      "valid_rate": 0.0
    },
    {
      "task_id": 374862420,
      "game_name": "gin_rummy",
      "seed": 949071605,
      "opponent": "random",
      "final_reward": 0.5,
      "total_turns": 48,
      "valid_turns": 0,
      "invalid_turns": 48,
      "valid_rate": 0.0
    },
    {
      "task_id": 60895143,
      "game_name": "goofspiel",
      "seed": 828276864,
      "opponent": "random",
      "final_reward": 0.0,
      "total_turns": 0,
      "valid_turns": 0,
      "invalid_turns": 0,
      "valid_rate": 0.0
    },
    {
      "task_id": 245567420,
      "game_name": "leduc_poker",
      "seed": 439542088,
      "opponent": "random",
      "final_reward": 0.5384615384615384,
      "total_turns": 1,
      "valid_turns": 0,
      "invalid_turns": 1,
      "valid_rate": 0.0
    },
    {
      "task_id": 381383524,
      "game_name": "gin_rummy",
      "seed": 367737405,
      "opponent": "random",
      "final_reward": 0.5,
      "total_turns": 48,
      "valid_turns": 0,
      "invalid_turns": 48,
      "valid_rate": 0.0
    },
    {
      "task_id": 42819503,
      "game_name": "goofspiel",
      "seed": 1386969407,
      "opponent": "random",
      "final_reward": 1.0,
      "total_turns": 0,
      "valid_turns": 0,
      "invalid_turns": 0,
      "valid_rate": 0.0
    },
    {
      "task_id": 271927435,
      "game_name": "leduc_poker",
      "seed": 1957407228,
      "opponent": "random",
      "final_reward": 0.6153846153846154,
      "total_turns": 3,
      "valid_turns": 0,
      "invalid_turns": 3,
      "valid_rate": 0.0
    },
    {
      "task_id": 343640017,
      "game_name": "gin_rummy",
      "seed": 1097363546,
      "opponent": "random",
      "final_reward": 0.5,
      "total_turns": 53,
      "valid_turns": 0,
      "invalid_turns": 53,
      "valid_rate": 0.0
    },
    {
      "task_id": 3869378,
      "game_name": "goofspiel",
      "seed": 190492655,
      "opponent": "random",
      "final_reward": 0.0,
      "total_turns": 0,
      "valid_turns": 0,
      "invalid_turns": 0,
      "valid_rate": 0.0
    },
    {
      "task_id": 225519054,
      "game_name": "leduc_poker",
      "seed": 1583572166,
      "opponent": "random",
      "final_reward": 0.38461538461538464,
      "total_turns": 2,
      "valid_turns": 0,
      "invalid_turns": 2,
      "valid_rate": 0.0
    },
    {
      "task_id": 310752980,
      "game_name": "gin_rummy",
      "seed": 900187885,
      "opponent": "random",
      "final_reward": 0.5,
      "total_turns": 51,
      "valid_turns": 0,
      "invalid_turns": 51,
      "valid_rate": 0.0
    },
    {
      "task_id": 70399158,
      "game_name": "goofspiel",
      "seed": 1484972987,
      "opponent": "random",
      "final_reward": 1.0,
      "total_turns": 0,
      "valid_turns": 0,
      "invalid_turns": 0,
      "valid_rate": 0.0
    },
    {
      "task_id": 225204080,
      "game_name": "leduc_poker",
      "seed": 865958133,
      "opponent": "random",
      "final_reward": 0.5,
      "total_turns": 2,
      "valid_turns": 0,
      "invalid_turns": 2,
      "valid_rate": 0.0
    },
    {
      "task_id": 333725836,
      "game_name": "gin_rummy",
      "seed": 1294165333,
      "opponent": "random",
      "final_reward": 0.5,
      "total_turns": 68,
      "valid_turns": 0,
      "invalid_turns": 68,
      "valid_rate": 0.0
    },
    {
      "task_id": 41907082,
      "game_name": "goofspiel",
      "seed": 1652152644,
      "opponent": "random",
      "final_reward": 1.0,
      "total_turns": 0,
      "valid_turns": 0,
      "invalid_turns": 0,
      "valid_rate": 0.0
    },
    {
      "task_id": 234177091,
      "game_name": "leduc_poker",
      "seed": 2070537872,
      "opponent": "random",
      "final_reward": 0.23076923076923078,
      "total_turns": 4,
      "valid_turns": 0,
      "invalid_turns": 4,
      "valid_rate": 0.0
    },
    {
      "task_id": 346162895,
      "game_name": "gin_rummy",
      "seed": 1030628967,
      "opponent": "random",
      "final_reward": 0.5,
      "total_turns": 77,
      "valid_turns": 0,
      "invalid_turns": 77,
      "valid_rate": 0.0
    },
    {
      "task_id": 5973078,
      "game_name": "goofspiel",
      "seed": 1313464150,
      "opponent": "random",
      "final_reward": 1.0,
      "total_turns": 0,
      "valid_turns": 0,
      "invalid_turns": 0,
      "valid_rate": 0.0
    },
    {
      "task_id": 274084666,
      "game_name": "leduc_poker",
      "seed": 310688215,
      "opponent": "random",
      "final_reward": 0.5,
      "total_turns": 3,
      "valid_turns": 0,
      "invalid_turns": 3,
      "valid_rate": 0.0
    },
    {
      "task_id": 301235938,
      "game_name": "gin_rummy",
      "seed": 1979683824,
      "opponent": "random",
      "final_reward": 0.5,
      "total_turns": 71,
      "valid_turns": 0,
      "invalid_turns": 71,
      "valid_rate": 0.0
    },
    {
      "task_id": 66478112,
      "game_name": "goofspiel",
      "seed": 1882048650,
      "opponent": "random",
      "final_reward": 0.0,
      "total_turns": 0,
      "valid_turns": 0,
      "invalid_turns": 0,
      "valid_rate": 0.0
    },
    {
      "task_id": 206371118,
      "game_name": "leduc_poker",
      "seed": 1770042721,
      "opponent": "random",
      "final_reward": 0.5384615384615384,
      "total_turns": 1,
      "valid_turns": 0,
      "invalid_turns": 1,
      "valid_rate": 0.0
    },
    {
      "task_id": 366247451,
      "game_name": "gin_rummy",
      "seed": 1977882589,
      "opponent": "random",
      "final_reward": 0.5,
      "total_turns": 46,
      "valid_turns": 0,
      "invalid_turns": 46,
      "valid_rate": 0.0
    },
    {
      "task_id": 59070377,
      "game_name": "goofspiel",
      "seed": 507337168,
      "opponent": "random",
      "final_reward": 1.0,
      "total_turns": 0,
      "valid_turns": 0,
      "invalid_turns": 0,
      "valid_rate": 0.0
    },
    {
      "task_id": 211491150,
      "game_name": "leduc_poker",
      "seed": 349941026,
      "opponent": "random",
      "final_reward": 0.6153846153846154,
      "total_turns": 2,
      "valid_turns": 0,
      "invalid_turns": 2,
      "valid_rate": 0.0
    },
    {
      "task_id": 332365853,
      "game_name": "gin_rummy",
      "seed": 424043987,
      "opponent": "random",
      "final_reward": 0.5,
      "total_turns": 25,
      "valid_turns": 0,
      "invalid_turns": 25,
      "valid_rate": 0.0
    },
    {
      "task_id": 20642106,
      "game_name": "goofspiel",
      "seed": 1778171632,
      "opponent": "random",
      "final_reward": 0.0,
      "total_turns": 0,
      "valid_turns": 0,
      "invalid_turns": 0,
      "valid_rate": 0.0
    },
    {
      "task_id": 228650992,
      "game_name": "leduc_poker",
      "seed": 1892533416,
      "opponent": "random",
      "final_reward": 0.38461538461538464,
      "total_turns": 2,
      "valid_turns": 0,
      "invalid_turns": 2,
      "valid_rate": 0.0
    },
    {
      "task_id": 382242811,
      "game_name": "gin_rummy",
      "seed": 331327998,
      "opponent": "random",
      "final_reward": 0.5,
      "total_turns": 65,
      "valid_turns": 0,
      "invalid_turns": 65,
      "valid_rate": 0.0
    },
    {
      "task_id": 57302324,
      "game_name": "goofspiel",
      "seed": 1694240186,
      "opponent": "random",
      "final_reward": 0.0,
      "total_turns": 0,
      "valid_turns": 0,
      "invalid_turns": 0,
      "valid_rate": 0.0
    },
    {
      "task_id": 205281693,
      "game_name": "leduc_poker",
      "seed": 774766559,
      "opponent": "random",
      "final_reward": 0.6153846153846154,
      "total_turns": 1,
      "valid_turns": 0,
      "invalid_turns": 1,
      "valid_rate": 0.0
    },
    {
      "task_id": 333517950,
      "game_name": "gin_rummy",
      "seed": 2104591761,
      "opponent": "random",
      "final_reward": 0.5,
      "total_turns": 58,
      "valid_turns": 0,
      "invalid_turns": 58,
      "valid_rate": 0.0
    },
    {
      "task_id": 29534678,
      "game_name": "goofspiel",
      "seed": 550122923,
      "opponent": "random",
      "final_reward": 1.0,
      "total_turns": 0,
      "valid_turns": 0,
      "invalid_turns": 0,
      "valid_rate": 0.0
    },
    {
      "task_id": 237446211,
      "game_name": "leduc_poker",
      "seed": 1512273227,
      "opponent": "random",
      "final_reward": 0.3076923076923077,
      "total_turns": 3,
      "valid_turns": 0,
      "invalid_turns": 3,
      "valid_rate": 0.0
    },
    {
      "task_id": 342895582,
      "game_name": "gin_rummy",
      "seed": 1867639416,
      "opponent": "random",
      "final_reward": 0.5,
      "total_turns": 80,
      "valid_turns": 0,
      "invalid_turns": 80,
      "valid_rate": 0.0
    },
    {
      "task_id": 14399599,
      "game_name": "goofspiel",
      "seed": 1226238020,
      "opponent": "random",
      "final_reward": 0.0,
      "total_turns": 0,
      "valid_turns": 0,
      "invalid_turns": 0,
      "valid_rate": 0.0
    },
    {
      "task_id": 281883819,
      "game_name": "leduc_poker",
      "seed": 864083196,
      "opponent": "random",
      "final_reward": 0.15384615384615385,
      "total_turns": 3,
      "valid_turns": 0,
      "invalid_turns": 3,
      "valid_rate": 0.0
    }
  ],
  "aggregated": {
    "total_valid_turns": 5,
    "total_invalid_turns": 3645,
    "avg_valid_rate": 0.0023652389277389278,
    "games_played": {
      "hex": 1,
      "goofspiel": 45,
      "othello": 1,
      "liars_dice": 2,
      "clobber": 1,
      "leduc_poker": 46,
      "backgammon": 18,
      "gin_rummy": 46
    }
  }
}